Metadata-Version: 2.1
Name: chaconprobabilidades
Version: 0.1
Summary: Gaussian distributions
Home-page: UNKNOWN
Author: Fernando Chacon
Author-email: francofer7775@gmail.com
License: UNKNOWN
Platform: UNKNOWN
